[
	{
		"label": "PhD in Software Process Improvement and Knowledge Management from Copenhagen Business School's Dept. of Informatics",
		"startYear": "2003",
		"endYear": "2009",
		"links": [
			{
				"link": "http://goo.gl/YlNDBq",
				"label": "Copenhagen Business School"
			},
			{
				"link": "http://openarchive.cbs.dk/bitstream/handle/10398/7902/Bo_Hansen_Hansen_1.pdf?sequence=4",
				"label": "Thesis (pdf)"
			}
		]
	},
		{	
		"label": "Courses from \"Diploma in specialized Business Studies\", Business Economics and Business Organisation",
		"startYear": "1994",
		"endYear": "1996",
		"links": [
			{
				"link": "http://brock.dk",
				"label": "Niels Brock"
			}
		]
	},
	{	
		"label": "Cand.merc.(dat.), MSc in Business Administration and Computer Science",
		"startYear": "1999",
		"endYear": "2002",
		"links": [
			{
				"link": "http://cbs.dk",
				"label": "Copenhagen Business School"
			},
						{
				"label": "Thesis (pdf)",
				"link": "assets/docs/HansenAndJacobsen2002.pdf"
			}
		]
	},	
	{	
		"label": "Ha.(dat.), BSc in Business Administration and Computer Science",
		"startYear": "1996",
		"endYear": "1999",
		"links": [
			{
				"link": "http://cbs.dk",
				"label": "Copenhagen Business School"
			}
		]
	},
	{
		"label": "Diploma in Specialised Business Studies, (Single Course), Applied Management",
		"startYear": "2009",
		"endYear": "2009",
		"links": [
			{
				"link": "http://markmanntraining.dk/",
				"label": "Markmann Training"	
			}
		]
	}
]